github_vulnerability_exporter/__init__.py
github_vulnerability_exporter/exporter.py
github_vulnerability_exporter-1.5.2.dist-info/LICENSE
github_vulnerability_exporter-1.5.2.dist-info/METADATA
github_vulnerability_exporter-1.5.2.dist-info/WHEEL
github_vulnerability_exporter-1.5.2.dist-info/entry_points.txt
github_vulnerability_exporter-1.5.2.dist-info/top_level.txt
github_vulnerability_exporter-1.5.2.dist-info/RECORD
