Metadata-Version: 2.1
Name: github-vulnerability-exporter
Version: 1.5.2
Summary: UNKNOWN
Home-page: https://github.com/ZeitOnline/github_vulnerability_exporter
Author: Wolfgang Schnerring
Author-email: wolfgang.schnerring@zeit.de
License: BSD
Platform: UNKNOWN
License-File: LICENSE
Requires-Dist: prometheus-client
Requires-Dist: requests
Requires-Dist: setuptools
